{
  "url": "https://www.learncpp.com/cpp-tutorial/function-overload-differentiation/",
  "title": "11.2 \u2014 Function overload differentiation",
  "sections": [
    {
      "heading": null,
      "content": [
        {
          "text": "In the prior lesson (11.1 -- Introduction to function overloading), we introduced the concept of function overloading, which allows us to create multiple functions with the same name, so long as each identically named function has different parameter types (or the functions can be otherwise differentiated).In this lesson, we\u2019ll take a closer look at how overloaded functions are differentiated. Overloaded functions that are not properly differentiated will cause the compiler to issue a compile error.How overloaded functions are differentiatedFunction propertyUsed for differentiationNotesNumber of parametersYesType of parametersYesExcludes typedefs, type aliases, and const qualifier on value parameters. Includes ellipses.Return typeNoNote that a function\u2019s return type is not used to differentiate overloaded functions. We\u2019ll discuss this more in a bit.For advanced readersFor member functions, additional function-level qualifiers are also considered:Function-level qualifierUsed for overloadingconst or volatileYesRef-qualifiersYesAs an example, a const member function can be differentiated from an otherwise identical non-const member function (even if they share the same set of parameters).Related contentWe cover ellipses in lesson20.5 -- Ellipsis (and why to avoid them).Overloading based on number of parametersAn overloaded function is differentiated so long as each overloaded function has a different number of parameters. For example:int add(int x, int y)\n{\n    return x + y;\n}\n\nint add(int x, int y, int z)\n{\n    return x + y + z;\n}The compiler can easily tell that a function call with two integer parameters should go toadd(int, int)and a function call with three integer parameters should go toadd(int, int, int).Overloading based on type of parametersA function can also be differentiated so long as each overloaded function\u2019s list of parameter types is distinct. For example, all of the following overloads are differentiated:int add(int x, int y); // integer version\ndouble add(double x, double y); // floating point version\ndouble add(int x, double y); // mixed version\ndouble add(double x, int y); // mixed versionBecause type aliases (or typedefs) are not distinct types, overloaded functions using type aliases are not distinct from overloads using the aliased type. For example, all of the following overloads are not differentiated (and will result in a compile error):typedef int Height; // typedef\nusing Age = int; // type alias\n\nvoid print(int value);\nvoid print(Age value); // not differentiated from print(int)\nvoid print(Height value); // not differentiated from print(int)For parameters passed by value, the const qualifier is also not considered. Therefore, the following functions are not considered to be differentiated:void print(int);\nvoid print(const int); // not differentiated from print(int)For advanced readersWe haven\u2019t covered ellipsis yet, but ellipsis parameters are considered to be a unique type of parameter:void foo(int x, int y);\nvoid foo(int x, ...); // differentiated from foo(int, int)Thus a call tofoo(4, 5)will match tofoo(int, int), notfoo(int, ...).The return type of a function is not considered for differentiationA function\u2019s return type is not considered when differentiating overloaded functions.Consider the case where you want to write a function that returns a random number, but you need a version that will return an int, and another version that will return a double. You might be tempted to do this:int getRandomValue();\ndouble getRandomValue();On Visual Studio 2019, this results in the following compiler error:error C2556: 'double getRandomValue(void)': overloaded function differs only by return type from 'int getRandomValue(void)'This makes sense. If you were the compiler, and you saw this statement:getRandomValue();Which of the two overloaded functions would you call? It\u2019s not clear.As an aside\u2026This was an intentional choice, as it ensures the behavior of a function call can be determined independently from the rest of the expression, making understanding complex expressions much simpler. Put another way, we can always determine which version of a function will be called based solely on the arguments in the function call. If return values were used for differentiation, then we wouldn\u2019t have an easy syntactic way to tell which overload of a function was being called -- we\u2019d also have to understand how the return value was being used, which requires a lot more analysis.The best way to address this is to give the functions different names:int getRandomInt();\ndouble getRandomDouble();Type signatureA function\u2019stype signature(generally called asignature) is defined as the parts of the function header that are used for differentiation of the function. In C++, this includes the function name, number of parameters, parameter type, and function-level qualifiers. It notably doesnotinclude the return type.Name manglingAs an aside\u2026When the compiler compiles a function, it performsname mangling, which means the compiled name of the function is altered (\u201cmangled\u201d) based on various criteria, such as the number and type of parameters, so that the linker has unique names to work with.For example, a function with prototypeint fcn()might compile to mangled name__fcn_v, whereasint fcn(int)might compile to mangled name__fcn_i. So while in the source code, the two overloaded functions share the namefcn(), in compiled code, the mangled names are unique (__fcn_vvs__fcn_i).There is no standardization on how names should be mangled, so different compilers will produce different mangled names.Next lesson11.3Function overload resolution and ambiguous matchesBack to table of contentsPrevious lesson11.1Introduction to function overloading"
        },
        {
          "text": "In this lesson, we\u2019ll take a closer look at how overloaded functions are differentiated. Overloaded functions that are not properly differentiated will cause the compiler to issue a compile error.How overloaded functions are differentiatedFunction propertyUsed for differentiationNotesNumber of parametersYesType of parametersYesExcludes typedefs, type aliases, and const qualifier on value parameters. Includes ellipses.Return typeNoNote that a function\u2019s return type is not used to differentiate overloaded functions. We\u2019ll discuss this more in a bit.For advanced readersFor member functions, additional function-level qualifiers are also considered:Function-level qualifierUsed for overloadingconst or volatileYesRef-qualifiersYesAs an example, a const member function can be differentiated from an otherwise identical non-const member function (even if they share the same set of parameters).Related contentWe cover ellipses in lesson20.5 -- Ellipsis (and why to avoid them).Overloading based on number of parametersAn overloaded function is differentiated so long as each overloaded function has a different number of parameters. For example:int add(int x, int y)\n{\n    return x + y;\n}\n\nint add(int x, int y, int z)\n{\n    return x + y + z;\n}The compiler can easily tell that a function call with two integer parameters should go toadd(int, int)and a function call with three integer parameters should go toadd(int, int, int).Overloading based on type of parametersA function can also be differentiated so long as each overloaded function\u2019s list of parameter types is distinct. For example, all of the following overloads are differentiated:int add(int x, int y); // integer version\ndouble add(double x, double y); // floating point version\ndouble add(int x, double y); // mixed version\ndouble add(double x, int y); // mixed versionBecause type aliases (or typedefs) are not distinct types, overloaded functions using type aliases are not distinct from overloads using the aliased type. For example, all of the following overloads are not differentiated (and will result in a compile error):typedef int Height; // typedef\nusing Age = int; // type alias\n\nvoid print(int value);\nvoid print(Age value); // not differentiated from print(int)\nvoid print(Height value); // not differentiated from print(int)For parameters passed by value, the const qualifier is also not considered. Therefore, the following functions are not considered to be differentiated:void print(int);\nvoid print(const int); // not differentiated from print(int)For advanced readersWe haven\u2019t covered ellipsis yet, but ellipsis parameters are considered to be a unique type of parameter:void foo(int x, int y);\nvoid foo(int x, ...); // differentiated from foo(int, int)Thus a call tofoo(4, 5)will match tofoo(int, int), notfoo(int, ...).The return type of a function is not considered for differentiationA function\u2019s return type is not considered when differentiating overloaded functions.Consider the case where you want to write a function that returns a random number, but you need a version that will return an int, and another version that will return a double. You might be tempted to do this:int getRandomValue();\ndouble getRandomValue();On Visual Studio 2019, this results in the following compiler error:error C2556: 'double getRandomValue(void)': overloaded function differs only by return type from 'int getRandomValue(void)'This makes sense. If you were the compiler, and you saw this statement:getRandomValue();Which of the two overloaded functions would you call? It\u2019s not clear.As an aside\u2026This was an intentional choice, as it ensures the behavior of a function call can be determined independently from the rest of the expression, making understanding complex expressions much simpler. Put another way, we can always determine which version of a function will be called based solely on the arguments in the function call. If return values were used for differentiation, then we wouldn\u2019t have an easy syntactic way to tell which overload of a function was being called -- we\u2019d also have to understand how the return value was being used, which requires a lot more analysis.The best way to address this is to give the functions different names:int getRandomInt();\ndouble getRandomDouble();Type signatureA function\u2019stype signature(generally called asignature) is defined as the parts of the function header that are used for differentiation of the function. In C++, this includes the function name, number of parameters, parameter type, and function-level qualifiers. It notably doesnotinclude the return type.Name manglingAs an aside\u2026When the compiler compiles a function, it performsname mangling, which means the compiled name of the function is altered (\u201cmangled\u201d) based on various criteria, such as the number and type of parameters, so that the linker has unique names to work with.For example, a function with prototypeint fcn()might compile to mangled name__fcn_v, whereasint fcn(int)might compile to mangled name__fcn_i. So while in the source code, the two overloaded functions share the namefcn(), in compiled code, the mangled names are unique (__fcn_vvs__fcn_i).There is no standardization on how names should be mangled, so different compilers will produce different mangled names.Next lesson11.3Function overload resolution and ambiguous matchesBack to table of contentsPrevious lesson11.1Introduction to function overloading"
        },
        {
          "text": "How overloaded functions are differentiatedFunction propertyUsed for differentiationNotesNumber of parametersYesType of parametersYesExcludes typedefs, type aliases, and const qualifier on value parameters. Includes ellipses.Return typeNoNote that a function\u2019s return type is not used to differentiate overloaded functions. We\u2019ll discuss this more in a bit.For advanced readersFor member functions, additional function-level qualifiers are also considered:Function-level qualifierUsed for overloadingconst or volatileYesRef-qualifiersYesAs an example, a const member function can be differentiated from an otherwise identical non-const member function (even if they share the same set of parameters).Related contentWe cover ellipses in lesson20.5 -- Ellipsis (and why to avoid them).Overloading based on number of parametersAn overloaded function is differentiated so long as each overloaded function has a different number of parameters. For example:int add(int x, int y)\n{\n    return x + y;\n}\n\nint add(int x, int y, int z)\n{\n    return x + y + z;\n}The compiler can easily tell that a function call with two integer parameters should go toadd(int, int)and a function call with three integer parameters should go toadd(int, int, int).Overloading based on type of parametersA function can also be differentiated so long as each overloaded function\u2019s list of parameter types is distinct. For example, all of the following overloads are differentiated:int add(int x, int y); // integer version\ndouble add(double x, double y); // floating point version\ndouble add(int x, double y); // mixed version\ndouble add(double x, int y); // mixed versionBecause type aliases (or typedefs) are not distinct types, overloaded functions using type aliases are not distinct from overloads using the aliased type. For example, all of the following overloads are not differentiated (and will result in a compile error):typedef int Height; // typedef\nusing Age = int; // type alias\n\nvoid print(int value);\nvoid print(Age value); // not differentiated from print(int)\nvoid print(Height value); // not differentiated from print(int)For parameters passed by value, the const qualifier is also not considered. Therefore, the following functions are not considered to be differentiated:void print(int);\nvoid print(const int); // not differentiated from print(int)For advanced readersWe haven\u2019t covered ellipsis yet, but ellipsis parameters are considered to be a unique type of parameter:void foo(int x, int y);\nvoid foo(int x, ...); // differentiated from foo(int, int)Thus a call tofoo(4, 5)will match tofoo(int, int), notfoo(int, ...).The return type of a function is not considered for differentiationA function\u2019s return type is not considered when differentiating overloaded functions.Consider the case where you want to write a function that returns a random number, but you need a version that will return an int, and another version that will return a double. You might be tempted to do this:int getRandomValue();\ndouble getRandomValue();On Visual Studio 2019, this results in the following compiler error:error C2556: 'double getRandomValue(void)': overloaded function differs only by return type from 'int getRandomValue(void)'This makes sense. If you were the compiler, and you saw this statement:getRandomValue();Which of the two overloaded functions would you call? It\u2019s not clear.As an aside\u2026This was an intentional choice, as it ensures the behavior of a function call can be determined independently from the rest of the expression, making understanding complex expressions much simpler. Put another way, we can always determine which version of a function will be called based solely on the arguments in the function call. If return values were used for differentiation, then we wouldn\u2019t have an easy syntactic way to tell which overload of a function was being called -- we\u2019d also have to understand how the return value was being used, which requires a lot more analysis.The best way to address this is to give the functions different names:int getRandomInt();\ndouble getRandomDouble();Type signatureA function\u2019stype signature(generally called asignature) is defined as the parts of the function header that are used for differentiation of the function. In C++, this includes the function name, number of parameters, parameter type, and function-level qualifiers. It notably doesnotinclude the return type.Name manglingAs an aside\u2026When the compiler compiles a function, it performsname mangling, which means the compiled name of the function is altered (\u201cmangled\u201d) based on various criteria, such as the number and type of parameters, so that the linker has unique names to work with.For example, a function with prototypeint fcn()might compile to mangled name__fcn_v, whereasint fcn(int)might compile to mangled name__fcn_i. So while in the source code, the two overloaded functions share the namefcn(), in compiled code, the mangled names are unique (__fcn_vvs__fcn_i).There is no standardization on how names should be mangled, so different compilers will produce different mangled names.Next lesson11.3Function overload resolution and ambiguous matchesBack to table of contentsPrevious lesson11.1Introduction to function overloading"
        },
        {
          "text": "Function propertyUsed for differentiationNotesNumber of parametersYesType of parametersYesExcludes typedefs, type aliases, and const qualifier on value parameters. Includes ellipses.Return typeNo"
        },
        {
          "text": "Function propertyUsed for differentiationNotesNumber of parametersYesType of parametersYesExcludes typedefs, type aliases, and const qualifier on value parameters. Includes ellipses.Return typeNo"
        },
        {
          "text": "Note that a function\u2019s return type is not used to differentiate overloaded functions. We\u2019ll discuss this more in a bit.For advanced readersFor member functions, additional function-level qualifiers are also considered:Function-level qualifierUsed for overloadingconst or volatileYesRef-qualifiersYesAs an example, a const member function can be differentiated from an otherwise identical non-const member function (even if they share the same set of parameters).Related contentWe cover ellipses in lesson20.5 -- Ellipsis (and why to avoid them).Overloading based on number of parametersAn overloaded function is differentiated so long as each overloaded function has a different number of parameters. For example:int add(int x, int y)\n{\n    return x + y;\n}\n\nint add(int x, int y, int z)\n{\n    return x + y + z;\n}The compiler can easily tell that a function call with two integer parameters should go toadd(int, int)and a function call with three integer parameters should go toadd(int, int, int).Overloading based on type of parametersA function can also be differentiated so long as each overloaded function\u2019s list of parameter types is distinct. For example, all of the following overloads are differentiated:int add(int x, int y); // integer version\ndouble add(double x, double y); // floating point version\ndouble add(int x, double y); // mixed version\ndouble add(double x, int y); // mixed versionBecause type aliases (or typedefs) are not distinct types, overloaded functions using type aliases are not distinct from overloads using the aliased type. For example, all of the following overloads are not differentiated (and will result in a compile error):typedef int Height; // typedef\nusing Age = int; // type alias\n\nvoid print(int value);\nvoid print(Age value); // not differentiated from print(int)\nvoid print(Height value); // not differentiated from print(int)For parameters passed by value, the const qualifier is also not considered. Therefore, the following functions are not considered to be differentiated:void print(int);\nvoid print(const int); // not differentiated from print(int)For advanced readersWe haven\u2019t covered ellipsis yet, but ellipsis parameters are considered to be a unique type of parameter:void foo(int x, int y);\nvoid foo(int x, ...); // differentiated from foo(int, int)Thus a call tofoo(4, 5)will match tofoo(int, int), notfoo(int, ...).The return type of a function is not considered for differentiationA function\u2019s return type is not considered when differentiating overloaded functions.Consider the case where you want to write a function that returns a random number, but you need a version that will return an int, and another version that will return a double. You might be tempted to do this:int getRandomValue();\ndouble getRandomValue();On Visual Studio 2019, this results in the following compiler error:error C2556: 'double getRandomValue(void)': overloaded function differs only by return type from 'int getRandomValue(void)'This makes sense. If you were the compiler, and you saw this statement:getRandomValue();Which of the two overloaded functions would you call? It\u2019s not clear.As an aside\u2026This was an intentional choice, as it ensures the behavior of a function call can be determined independently from the rest of the expression, making understanding complex expressions much simpler. Put another way, we can always determine which version of a function will be called based solely on the arguments in the function call. If return values were used for differentiation, then we wouldn\u2019t have an easy syntactic way to tell which overload of a function was being called -- we\u2019d also have to understand how the return value was being used, which requires a lot more analysis.The best way to address this is to give the functions different names:int getRandomInt();\ndouble getRandomDouble();Type signatureA function\u2019stype signature(generally called asignature) is defined as the parts of the function header that are used for differentiation of the function. In C++, this includes the function name, number of parameters, parameter type, and function-level qualifiers. It notably doesnotinclude the return type.Name manglingAs an aside\u2026When the compiler compiles a function, it performsname mangling, which means the compiled name of the function is altered (\u201cmangled\u201d) based on various criteria, such as the number and type of parameters, so that the linker has unique names to work with.For example, a function with prototypeint fcn()might compile to mangled name__fcn_v, whereasint fcn(int)might compile to mangled name__fcn_i. So while in the source code, the two overloaded functions share the namefcn(), in compiled code, the mangled names are unique (__fcn_vvs__fcn_i).There is no standardization on how names should be mangled, so different compilers will produce different mangled names.Next lesson11.3Function overload resolution and ambiguous matchesBack to table of contentsPrevious lesson11.1Introduction to function overloading"
        },
        {
          "text": "For advanced readersFor member functions, additional function-level qualifiers are also considered:Function-level qualifierUsed for overloadingconst or volatileYesRef-qualifiersYesAs an example, a const member function can be differentiated from an otherwise identical non-const member function (even if they share the same set of parameters)."
        },
        {
          "text": "For member functions, additional function-level qualifiers are also considered:Function-level qualifierUsed for overloadingconst or volatileYesRef-qualifiersYesAs an example, a const member function can be differentiated from an otherwise identical non-const member function (even if they share the same set of parameters)."
        },
        {
          "text": "Function-level qualifierUsed for overloadingconst or volatileYesRef-qualifiersYes"
        },
        {
          "text": "Function-level qualifierUsed for overloadingconst or volatileYesRef-qualifiersYes"
        },
        {
          "text": "As an example, a const member function can be differentiated from an otherwise identical non-const member function (even if they share the same set of parameters)."
        },
        {
          "text": "Related contentWe cover ellipses in lesson20.5 -- Ellipsis (and why to avoid them)."
        },
        {
          "text": "We cover ellipses in lesson20.5 -- Ellipsis (and why to avoid them)."
        },
        {
          "text": "Overloading based on number of parametersAn overloaded function is differentiated so long as each overloaded function has a different number of parameters. For example:int add(int x, int y)\n{\n    return x + y;\n}\n\nint add(int x, int y, int z)\n{\n    return x + y + z;\n}The compiler can easily tell that a function call with two integer parameters should go toadd(int, int)and a function call with three integer parameters should go toadd(int, int, int).Overloading based on type of parametersA function can also be differentiated so long as each overloaded function\u2019s list of parameter types is distinct. For example, all of the following overloads are differentiated:int add(int x, int y); // integer version\ndouble add(double x, double y); // floating point version\ndouble add(int x, double y); // mixed version\ndouble add(double x, int y); // mixed versionBecause type aliases (or typedefs) are not distinct types, overloaded functions using type aliases are not distinct from overloads using the aliased type. For example, all of the following overloads are not differentiated (and will result in a compile error):typedef int Height; // typedef\nusing Age = int; // type alias\n\nvoid print(int value);\nvoid print(Age value); // not differentiated from print(int)\nvoid print(Height value); // not differentiated from print(int)For parameters passed by value, the const qualifier is also not considered. Therefore, the following functions are not considered to be differentiated:void print(int);\nvoid print(const int); // not differentiated from print(int)For advanced readersWe haven\u2019t covered ellipsis yet, but ellipsis parameters are considered to be a unique type of parameter:void foo(int x, int y);\nvoid foo(int x, ...); // differentiated from foo(int, int)Thus a call tofoo(4, 5)will match tofoo(int, int), notfoo(int, ...).The return type of a function is not considered for differentiationA function\u2019s return type is not considered when differentiating overloaded functions.Consider the case where you want to write a function that returns a random number, but you need a version that will return an int, and another version that will return a double. You might be tempted to do this:int getRandomValue();\ndouble getRandomValue();On Visual Studio 2019, this results in the following compiler error:error C2556: 'double getRandomValue(void)': overloaded function differs only by return type from 'int getRandomValue(void)'This makes sense. If you were the compiler, and you saw this statement:getRandomValue();Which of the two overloaded functions would you call? It\u2019s not clear.As an aside\u2026This was an intentional choice, as it ensures the behavior of a function call can be determined independently from the rest of the expression, making understanding complex expressions much simpler. Put another way, we can always determine which version of a function will be called based solely on the arguments in the function call. If return values were used for differentiation, then we wouldn\u2019t have an easy syntactic way to tell which overload of a function was being called -- we\u2019d also have to understand how the return value was being used, which requires a lot more analysis.The best way to address this is to give the functions different names:int getRandomInt();\ndouble getRandomDouble();Type signatureA function\u2019stype signature(generally called asignature) is defined as the parts of the function header that are used for differentiation of the function. In C++, this includes the function name, number of parameters, parameter type, and function-level qualifiers. It notably doesnotinclude the return type.Name manglingAs an aside\u2026When the compiler compiles a function, it performsname mangling, which means the compiled name of the function is altered (\u201cmangled\u201d) based on various criteria, such as the number and type of parameters, so that the linker has unique names to work with.For example, a function with prototypeint fcn()might compile to mangled name__fcn_v, whereasint fcn(int)might compile to mangled name__fcn_i. So while in the source code, the two overloaded functions share the namefcn(), in compiled code, the mangled names are unique (__fcn_vvs__fcn_i).There is no standardization on how names should be mangled, so different compilers will produce different mangled names.Next lesson11.3Function overload resolution and ambiguous matchesBack to table of contentsPrevious lesson11.1Introduction to function overloading"
        },
        {
          "text": "An overloaded function is differentiated so long as each overloaded function has a different number of parameters. For example:int add(int x, int y)\n{\n    return x + y;\n}\n\nint add(int x, int y, int z)\n{\n    return x + y + z;\n}The compiler can easily tell that a function call with two integer parameters should go toadd(int, int)and a function call with three integer parameters should go toadd(int, int, int).Overloading based on type of parametersA function can also be differentiated so long as each overloaded function\u2019s list of parameter types is distinct. For example, all of the following overloads are differentiated:int add(int x, int y); // integer version\ndouble add(double x, double y); // floating point version\ndouble add(int x, double y); // mixed version\ndouble add(double x, int y); // mixed versionBecause type aliases (or typedefs) are not distinct types, overloaded functions using type aliases are not distinct from overloads using the aliased type. For example, all of the following overloads are not differentiated (and will result in a compile error):typedef int Height; // typedef\nusing Age = int; // type alias\n\nvoid print(int value);\nvoid print(Age value); // not differentiated from print(int)\nvoid print(Height value); // not differentiated from print(int)For parameters passed by value, the const qualifier is also not considered. Therefore, the following functions are not considered to be differentiated:void print(int);\nvoid print(const int); // not differentiated from print(int)For advanced readersWe haven\u2019t covered ellipsis yet, but ellipsis parameters are considered to be a unique type of parameter:void foo(int x, int y);\nvoid foo(int x, ...); // differentiated from foo(int, int)Thus a call tofoo(4, 5)will match tofoo(int, int), notfoo(int, ...).The return type of a function is not considered for differentiationA function\u2019s return type is not considered when differentiating overloaded functions.Consider the case where you want to write a function that returns a random number, but you need a version that will return an int, and another version that will return a double. You might be tempted to do this:int getRandomValue();\ndouble getRandomValue();On Visual Studio 2019, this results in the following compiler error:error C2556: 'double getRandomValue(void)': overloaded function differs only by return type from 'int getRandomValue(void)'This makes sense. If you were the compiler, and you saw this statement:getRandomValue();Which of the two overloaded functions would you call? It\u2019s not clear.As an aside\u2026This was an intentional choice, as it ensures the behavior of a function call can be determined independently from the rest of the expression, making understanding complex expressions much simpler. Put another way, we can always determine which version of a function will be called based solely on the arguments in the function call. If return values were used for differentiation, then we wouldn\u2019t have an easy syntactic way to tell which overload of a function was being called -- we\u2019d also have to understand how the return value was being used, which requires a lot more analysis.The best way to address this is to give the functions different names:int getRandomInt();\ndouble getRandomDouble();Type signatureA function\u2019stype signature(generally called asignature) is defined as the parts of the function header that are used for differentiation of the function. In C++, this includes the function name, number of parameters, parameter type, and function-level qualifiers. It notably doesnotinclude the return type.Name manglingAs an aside\u2026When the compiler compiles a function, it performsname mangling, which means the compiled name of the function is altered (\u201cmangled\u201d) based on various criteria, such as the number and type of parameters, so that the linker has unique names to work with.For example, a function with prototypeint fcn()might compile to mangled name__fcn_v, whereasint fcn(int)might compile to mangled name__fcn_i. So while in the source code, the two overloaded functions share the namefcn(), in compiled code, the mangled names are unique (__fcn_vvs__fcn_i).There is no standardization on how names should be mangled, so different compilers will produce different mangled names.Next lesson11.3Function overload resolution and ambiguous matchesBack to table of contentsPrevious lesson11.1Introduction to function overloading"
        },
        {
          "code": "int add(int x, int y)\n{\n    return x + y;\n}\n\nint add(int x, int y, int z)\n{\n    return x + y + z;\n}"
        },
        {
          "text": "The compiler can easily tell that a function call with two integer parameters should go toadd(int, int)and a function call with three integer parameters should go toadd(int, int, int).Overloading based on type of parametersA function can also be differentiated so long as each overloaded function\u2019s list of parameter types is distinct. For example, all of the following overloads are differentiated:int add(int x, int y); // integer version\ndouble add(double x, double y); // floating point version\ndouble add(int x, double y); // mixed version\ndouble add(double x, int y); // mixed versionBecause type aliases (or typedefs) are not distinct types, overloaded functions using type aliases are not distinct from overloads using the aliased type. For example, all of the following overloads are not differentiated (and will result in a compile error):typedef int Height; // typedef\nusing Age = int; // type alias\n\nvoid print(int value);\nvoid print(Age value); // not differentiated from print(int)\nvoid print(Height value); // not differentiated from print(int)For parameters passed by value, the const qualifier is also not considered. Therefore, the following functions are not considered to be differentiated:void print(int);\nvoid print(const int); // not differentiated from print(int)For advanced readersWe haven\u2019t covered ellipsis yet, but ellipsis parameters are considered to be a unique type of parameter:void foo(int x, int y);\nvoid foo(int x, ...); // differentiated from foo(int, int)Thus a call tofoo(4, 5)will match tofoo(int, int), notfoo(int, ...).The return type of a function is not considered for differentiationA function\u2019s return type is not considered when differentiating overloaded functions.Consider the case where you want to write a function that returns a random number, but you need a version that will return an int, and another version that will return a double. You might be tempted to do this:int getRandomValue();\ndouble getRandomValue();On Visual Studio 2019, this results in the following compiler error:error C2556: 'double getRandomValue(void)': overloaded function differs only by return type from 'int getRandomValue(void)'This makes sense. If you were the compiler, and you saw this statement:getRandomValue();Which of the two overloaded functions would you call? It\u2019s not clear.As an aside\u2026This was an intentional choice, as it ensures the behavior of a function call can be determined independently from the rest of the expression, making understanding complex expressions much simpler. Put another way, we can always determine which version of a function will be called based solely on the arguments in the function call. If return values were used for differentiation, then we wouldn\u2019t have an easy syntactic way to tell which overload of a function was being called -- we\u2019d also have to understand how the return value was being used, which requires a lot more analysis.The best way to address this is to give the functions different names:int getRandomInt();\ndouble getRandomDouble();Type signatureA function\u2019stype signature(generally called asignature) is defined as the parts of the function header that are used for differentiation of the function. In C++, this includes the function name, number of parameters, parameter type, and function-level qualifiers. It notably doesnotinclude the return type.Name manglingAs an aside\u2026When the compiler compiles a function, it performsname mangling, which means the compiled name of the function is altered (\u201cmangled\u201d) based on various criteria, such as the number and type of parameters, so that the linker has unique names to work with.For example, a function with prototypeint fcn()might compile to mangled name__fcn_v, whereasint fcn(int)might compile to mangled name__fcn_i. So while in the source code, the two overloaded functions share the namefcn(), in compiled code, the mangled names are unique (__fcn_vvs__fcn_i).There is no standardization on how names should be mangled, so different compilers will produce different mangled names.Next lesson11.3Function overload resolution and ambiguous matchesBack to table of contentsPrevious lesson11.1Introduction to function overloading"
        },
        {
          "text": "Overloading based on type of parametersA function can also be differentiated so long as each overloaded function\u2019s list of parameter types is distinct. For example, all of the following overloads are differentiated:int add(int x, int y); // integer version\ndouble add(double x, double y); // floating point version\ndouble add(int x, double y); // mixed version\ndouble add(double x, int y); // mixed versionBecause type aliases (or typedefs) are not distinct types, overloaded functions using type aliases are not distinct from overloads using the aliased type. For example, all of the following overloads are not differentiated (and will result in a compile error):typedef int Height; // typedef\nusing Age = int; // type alias\n\nvoid print(int value);\nvoid print(Age value); // not differentiated from print(int)\nvoid print(Height value); // not differentiated from print(int)For parameters passed by value, the const qualifier is also not considered. Therefore, the following functions are not considered to be differentiated:void print(int);\nvoid print(const int); // not differentiated from print(int)For advanced readersWe haven\u2019t covered ellipsis yet, but ellipsis parameters are considered to be a unique type of parameter:void foo(int x, int y);\nvoid foo(int x, ...); // differentiated from foo(int, int)Thus a call tofoo(4, 5)will match tofoo(int, int), notfoo(int, ...).The return type of a function is not considered for differentiationA function\u2019s return type is not considered when differentiating overloaded functions.Consider the case where you want to write a function that returns a random number, but you need a version that will return an int, and another version that will return a double. You might be tempted to do this:int getRandomValue();\ndouble getRandomValue();On Visual Studio 2019, this results in the following compiler error:error C2556: 'double getRandomValue(void)': overloaded function differs only by return type from 'int getRandomValue(void)'This makes sense. If you were the compiler, and you saw this statement:getRandomValue();Which of the two overloaded functions would you call? It\u2019s not clear.As an aside\u2026This was an intentional choice, as it ensures the behavior of a function call can be determined independently from the rest of the expression, making understanding complex expressions much simpler. Put another way, we can always determine which version of a function will be called based solely on the arguments in the function call. If return values were used for differentiation, then we wouldn\u2019t have an easy syntactic way to tell which overload of a function was being called -- we\u2019d also have to understand how the return value was being used, which requires a lot more analysis.The best way to address this is to give the functions different names:int getRandomInt();\ndouble getRandomDouble();Type signatureA function\u2019stype signature(generally called asignature) is defined as the parts of the function header that are used for differentiation of the function. In C++, this includes the function name, number of parameters, parameter type, and function-level qualifiers. It notably doesnotinclude the return type.Name manglingAs an aside\u2026When the compiler compiles a function, it performsname mangling, which means the compiled name of the function is altered (\u201cmangled\u201d) based on various criteria, such as the number and type of parameters, so that the linker has unique names to work with.For example, a function with prototypeint fcn()might compile to mangled name__fcn_v, whereasint fcn(int)might compile to mangled name__fcn_i. So while in the source code, the two overloaded functions share the namefcn(), in compiled code, the mangled names are unique (__fcn_vvs__fcn_i).There is no standardization on how names should be mangled, so different compilers will produce different mangled names.Next lesson11.3Function overload resolution and ambiguous matchesBack to table of contentsPrevious lesson11.1Introduction to function overloading"
        },
        {
          "text": "A function can also be differentiated so long as each overloaded function\u2019s list of parameter types is distinct. For example, all of the following overloads are differentiated:int add(int x, int y); // integer version\ndouble add(double x, double y); // floating point version\ndouble add(int x, double y); // mixed version\ndouble add(double x, int y); // mixed versionBecause type aliases (or typedefs) are not distinct types, overloaded functions using type aliases are not distinct from overloads using the aliased type. For example, all of the following overloads are not differentiated (and will result in a compile error):typedef int Height; // typedef\nusing Age = int; // type alias\n\nvoid print(int value);\nvoid print(Age value); // not differentiated from print(int)\nvoid print(Height value); // not differentiated from print(int)For parameters passed by value, the const qualifier is also not considered. Therefore, the following functions are not considered to be differentiated:void print(int);\nvoid print(const int); // not differentiated from print(int)For advanced readersWe haven\u2019t covered ellipsis yet, but ellipsis parameters are considered to be a unique type of parameter:void foo(int x, int y);\nvoid foo(int x, ...); // differentiated from foo(int, int)Thus a call tofoo(4, 5)will match tofoo(int, int), notfoo(int, ...).The return type of a function is not considered for differentiationA function\u2019s return type is not considered when differentiating overloaded functions.Consider the case where you want to write a function that returns a random number, but you need a version that will return an int, and another version that will return a double. You might be tempted to do this:int getRandomValue();\ndouble getRandomValue();On Visual Studio 2019, this results in the following compiler error:error C2556: 'double getRandomValue(void)': overloaded function differs only by return type from 'int getRandomValue(void)'This makes sense. If you were the compiler, and you saw this statement:getRandomValue();Which of the two overloaded functions would you call? It\u2019s not clear.As an aside\u2026This was an intentional choice, as it ensures the behavior of a function call can be determined independently from the rest of the expression, making understanding complex expressions much simpler. Put another way, we can always determine which version of a function will be called based solely on the arguments in the function call. If return values were used for differentiation, then we wouldn\u2019t have an easy syntactic way to tell which overload of a function was being called -- we\u2019d also have to understand how the return value was being used, which requires a lot more analysis.The best way to address this is to give the functions different names:int getRandomInt();\ndouble getRandomDouble();Type signatureA function\u2019stype signature(generally called asignature) is defined as the parts of the function header that are used for differentiation of the function. In C++, this includes the function name, number of parameters, parameter type, and function-level qualifiers. It notably doesnotinclude the return type.Name manglingAs an aside\u2026When the compiler compiles a function, it performsname mangling, which means the compiled name of the function is altered (\u201cmangled\u201d) based on various criteria, such as the number and type of parameters, so that the linker has unique names to work with.For example, a function with prototypeint fcn()might compile to mangled name__fcn_v, whereasint fcn(int)might compile to mangled name__fcn_i. So while in the source code, the two overloaded functions share the namefcn(), in compiled code, the mangled names are unique (__fcn_vvs__fcn_i).There is no standardization on how names should be mangled, so different compilers will produce different mangled names.Next lesson11.3Function overload resolution and ambiguous matchesBack to table of contentsPrevious lesson11.1Introduction to function overloading"
        },
        {
          "code": "int add(int x, int y); // integer version\ndouble add(double x, double y); // floating point version\ndouble add(int x, double y); // mixed version\ndouble add(double x, int y); // mixed version"
        },
        {
          "text": "Because type aliases (or typedefs) are not distinct types, overloaded functions using type aliases are not distinct from overloads using the aliased type. For example, all of the following overloads are not differentiated (and will result in a compile error):typedef int Height; // typedef\nusing Age = int; // type alias\n\nvoid print(int value);\nvoid print(Age value); // not differentiated from print(int)\nvoid print(Height value); // not differentiated from print(int)For parameters passed by value, the const qualifier is also not considered. Therefore, the following functions are not considered to be differentiated:void print(int);\nvoid print(const int); // not differentiated from print(int)For advanced readersWe haven\u2019t covered ellipsis yet, but ellipsis parameters are considered to be a unique type of parameter:void foo(int x, int y);\nvoid foo(int x, ...); // differentiated from foo(int, int)Thus a call tofoo(4, 5)will match tofoo(int, int), notfoo(int, ...).The return type of a function is not considered for differentiationA function\u2019s return type is not considered when differentiating overloaded functions.Consider the case where you want to write a function that returns a random number, but you need a version that will return an int, and another version that will return a double. You might be tempted to do this:int getRandomValue();\ndouble getRandomValue();On Visual Studio 2019, this results in the following compiler error:error C2556: 'double getRandomValue(void)': overloaded function differs only by return type from 'int getRandomValue(void)'This makes sense. If you were the compiler, and you saw this statement:getRandomValue();Which of the two overloaded functions would you call? It\u2019s not clear.As an aside\u2026This was an intentional choice, as it ensures the behavior of a function call can be determined independently from the rest of the expression, making understanding complex expressions much simpler. Put another way, we can always determine which version of a function will be called based solely on the arguments in the function call. If return values were used for differentiation, then we wouldn\u2019t have an easy syntactic way to tell which overload of a function was being called -- we\u2019d also have to understand how the return value was being used, which requires a lot more analysis.The best way to address this is to give the functions different names:int getRandomInt();\ndouble getRandomDouble();Type signatureA function\u2019stype signature(generally called asignature) is defined as the parts of the function header that are used for differentiation of the function. In C++, this includes the function name, number of parameters, parameter type, and function-level qualifiers. It notably doesnotinclude the return type.Name manglingAs an aside\u2026When the compiler compiles a function, it performsname mangling, which means the compiled name of the function is altered (\u201cmangled\u201d) based on various criteria, such as the number and type of parameters, so that the linker has unique names to work with.For example, a function with prototypeint fcn()might compile to mangled name__fcn_v, whereasint fcn(int)might compile to mangled name__fcn_i. So while in the source code, the two overloaded functions share the namefcn(), in compiled code, the mangled names are unique (__fcn_vvs__fcn_i).There is no standardization on how names should be mangled, so different compilers will produce different mangled names.Next lesson11.3Function overload resolution and ambiguous matchesBack to table of contentsPrevious lesson11.1Introduction to function overloading"
        },
        {
          "code": "typedef int Height; // typedef\nusing Age = int; // type alias\n\nvoid print(int value);\nvoid print(Age value); // not differentiated from print(int)\nvoid print(Height value); // not differentiated from print(int)"
        },
        {
          "text": "For parameters passed by value, the const qualifier is also not considered. Therefore, the following functions are not considered to be differentiated:void print(int);\nvoid print(const int); // not differentiated from print(int)For advanced readersWe haven\u2019t covered ellipsis yet, but ellipsis parameters are considered to be a unique type of parameter:void foo(int x, int y);\nvoid foo(int x, ...); // differentiated from foo(int, int)Thus a call tofoo(4, 5)will match tofoo(int, int), notfoo(int, ...).The return type of a function is not considered for differentiationA function\u2019s return type is not considered when differentiating overloaded functions.Consider the case where you want to write a function that returns a random number, but you need a version that will return an int, and another version that will return a double. You might be tempted to do this:int getRandomValue();\ndouble getRandomValue();On Visual Studio 2019, this results in the following compiler error:error C2556: 'double getRandomValue(void)': overloaded function differs only by return type from 'int getRandomValue(void)'This makes sense. If you were the compiler, and you saw this statement:getRandomValue();Which of the two overloaded functions would you call? It\u2019s not clear.As an aside\u2026This was an intentional choice, as it ensures the behavior of a function call can be determined independently from the rest of the expression, making understanding complex expressions much simpler. Put another way, we can always determine which version of a function will be called based solely on the arguments in the function call. If return values were used for differentiation, then we wouldn\u2019t have an easy syntactic way to tell which overload of a function was being called -- we\u2019d also have to understand how the return value was being used, which requires a lot more analysis.The best way to address this is to give the functions different names:int getRandomInt();\ndouble getRandomDouble();Type signatureA function\u2019stype signature(generally called asignature) is defined as the parts of the function header that are used for differentiation of the function. In C++, this includes the function name, number of parameters, parameter type, and function-level qualifiers. It notably doesnotinclude the return type.Name manglingAs an aside\u2026When the compiler compiles a function, it performsname mangling, which means the compiled name of the function is altered (\u201cmangled\u201d) based on various criteria, such as the number and type of parameters, so that the linker has unique names to work with.For example, a function with prototypeint fcn()might compile to mangled name__fcn_v, whereasint fcn(int)might compile to mangled name__fcn_i. So while in the source code, the two overloaded functions share the namefcn(), in compiled code, the mangled names are unique (__fcn_vvs__fcn_i).There is no standardization on how names should be mangled, so different compilers will produce different mangled names.Next lesson11.3Function overload resolution and ambiguous matchesBack to table of contentsPrevious lesson11.1Introduction to function overloading"
        },
        {
          "code": "void print(int);\nvoid print(const int); // not differentiated from print(int)"
        },
        {
          "text": "For advanced readersWe haven\u2019t covered ellipsis yet, but ellipsis parameters are considered to be a unique type of parameter:void foo(int x, int y);\nvoid foo(int x, ...); // differentiated from foo(int, int)Thus a call tofoo(4, 5)will match tofoo(int, int), notfoo(int, ...)."
        },
        {
          "text": "We haven\u2019t covered ellipsis yet, but ellipsis parameters are considered to be a unique type of parameter:void foo(int x, int y);\nvoid foo(int x, ...); // differentiated from foo(int, int)Thus a call tofoo(4, 5)will match tofoo(int, int), notfoo(int, ...)."
        },
        {
          "code": "void foo(int x, int y);\nvoid foo(int x, ...); // differentiated from foo(int, int)"
        },
        {
          "text": "Thus a call tofoo(4, 5)will match tofoo(int, int), notfoo(int, ...)."
        },
        {
          "text": "The return type of a function is not considered for differentiationA function\u2019s return type is not considered when differentiating overloaded functions.Consider the case where you want to write a function that returns a random number, but you need a version that will return an int, and another version that will return a double. You might be tempted to do this:int getRandomValue();\ndouble getRandomValue();On Visual Studio 2019, this results in the following compiler error:error C2556: 'double getRandomValue(void)': overloaded function differs only by return type from 'int getRandomValue(void)'This makes sense. If you were the compiler, and you saw this statement:getRandomValue();Which of the two overloaded functions would you call? It\u2019s not clear.As an aside\u2026This was an intentional choice, as it ensures the behavior of a function call can be determined independently from the rest of the expression, making understanding complex expressions much simpler. Put another way, we can always determine which version of a function will be called based solely on the arguments in the function call. If return values were used for differentiation, then we wouldn\u2019t have an easy syntactic way to tell which overload of a function was being called -- we\u2019d also have to understand how the return value was being used, which requires a lot more analysis.The best way to address this is to give the functions different names:int getRandomInt();\ndouble getRandomDouble();Type signatureA function\u2019stype signature(generally called asignature) is defined as the parts of the function header that are used for differentiation of the function. In C++, this includes the function name, number of parameters, parameter type, and function-level qualifiers. It notably doesnotinclude the return type.Name manglingAs an aside\u2026When the compiler compiles a function, it performsname mangling, which means the compiled name of the function is altered (\u201cmangled\u201d) based on various criteria, such as the number and type of parameters, so that the linker has unique names to work with.For example, a function with prototypeint fcn()might compile to mangled name__fcn_v, whereasint fcn(int)might compile to mangled name__fcn_i. So while in the source code, the two overloaded functions share the namefcn(), in compiled code, the mangled names are unique (__fcn_vvs__fcn_i).There is no standardization on how names should be mangled, so different compilers will produce different mangled names.Next lesson11.3Function overload resolution and ambiguous matchesBack to table of contentsPrevious lesson11.1Introduction to function overloading"
        },
        {
          "text": "A function\u2019s return type is not considered when differentiating overloaded functions.Consider the case where you want to write a function that returns a random number, but you need a version that will return an int, and another version that will return a double. You might be tempted to do this:int getRandomValue();\ndouble getRandomValue();On Visual Studio 2019, this results in the following compiler error:error C2556: 'double getRandomValue(void)': overloaded function differs only by return type from 'int getRandomValue(void)'This makes sense. If you were the compiler, and you saw this statement:getRandomValue();Which of the two overloaded functions would you call? It\u2019s not clear.As an aside\u2026This was an intentional choice, as it ensures the behavior of a function call can be determined independently from the rest of the expression, making understanding complex expressions much simpler. Put another way, we can always determine which version of a function will be called based solely on the arguments in the function call. If return values were used for differentiation, then we wouldn\u2019t have an easy syntactic way to tell which overload of a function was being called -- we\u2019d also have to understand how the return value was being used, which requires a lot more analysis.The best way to address this is to give the functions different names:int getRandomInt();\ndouble getRandomDouble();Type signatureA function\u2019stype signature(generally called asignature) is defined as the parts of the function header that are used for differentiation of the function. In C++, this includes the function name, number of parameters, parameter type, and function-level qualifiers. It notably doesnotinclude the return type.Name manglingAs an aside\u2026When the compiler compiles a function, it performsname mangling, which means the compiled name of the function is altered (\u201cmangled\u201d) based on various criteria, such as the number and type of parameters, so that the linker has unique names to work with.For example, a function with prototypeint fcn()might compile to mangled name__fcn_v, whereasint fcn(int)might compile to mangled name__fcn_i. So while in the source code, the two overloaded functions share the namefcn(), in compiled code, the mangled names are unique (__fcn_vvs__fcn_i).There is no standardization on how names should be mangled, so different compilers will produce different mangled names.Next lesson11.3Function overload resolution and ambiguous matchesBack to table of contentsPrevious lesson11.1Introduction to function overloading"
        },
        {
          "text": "Consider the case where you want to write a function that returns a random number, but you need a version that will return an int, and another version that will return a double. You might be tempted to do this:int getRandomValue();\ndouble getRandomValue();On Visual Studio 2019, this results in the following compiler error:error C2556: 'double getRandomValue(void)': overloaded function differs only by return type from 'int getRandomValue(void)'This makes sense. If you were the compiler, and you saw this statement:getRandomValue();Which of the two overloaded functions would you call? It\u2019s not clear.As an aside\u2026This was an intentional choice, as it ensures the behavior of a function call can be determined independently from the rest of the expression, making understanding complex expressions much simpler. Put another way, we can always determine which version of a function will be called based solely on the arguments in the function call. If return values were used for differentiation, then we wouldn\u2019t have an easy syntactic way to tell which overload of a function was being called -- we\u2019d also have to understand how the return value was being used, which requires a lot more analysis.The best way to address this is to give the functions different names:int getRandomInt();\ndouble getRandomDouble();Type signatureA function\u2019stype signature(generally called asignature) is defined as the parts of the function header that are used for differentiation of the function. In C++, this includes the function name, number of parameters, parameter type, and function-level qualifiers. It notably doesnotinclude the return type.Name manglingAs an aside\u2026When the compiler compiles a function, it performsname mangling, which means the compiled name of the function is altered (\u201cmangled\u201d) based on various criteria, such as the number and type of parameters, so that the linker has unique names to work with.For example, a function with prototypeint fcn()might compile to mangled name__fcn_v, whereasint fcn(int)might compile to mangled name__fcn_i. So while in the source code, the two overloaded functions share the namefcn(), in compiled code, the mangled names are unique (__fcn_vvs__fcn_i).There is no standardization on how names should be mangled, so different compilers will produce different mangled names.Next lesson11.3Function overload resolution and ambiguous matchesBack to table of contentsPrevious lesson11.1Introduction to function overloading"
        },
        {
          "code": "int getRandomValue();\ndouble getRandomValue();"
        },
        {
          "text": "On Visual Studio 2019, this results in the following compiler error:error C2556: 'double getRandomValue(void)': overloaded function differs only by return type from 'int getRandomValue(void)'This makes sense. If you were the compiler, and you saw this statement:getRandomValue();Which of the two overloaded functions would you call? It\u2019s not clear.As an aside\u2026This was an intentional choice, as it ensures the behavior of a function call can be determined independently from the rest of the expression, making understanding complex expressions much simpler. Put another way, we can always determine which version of a function will be called based solely on the arguments in the function call. If return values were used for differentiation, then we wouldn\u2019t have an easy syntactic way to tell which overload of a function was being called -- we\u2019d also have to understand how the return value was being used, which requires a lot more analysis.The best way to address this is to give the functions different names:int getRandomInt();\ndouble getRandomDouble();Type signatureA function\u2019stype signature(generally called asignature) is defined as the parts of the function header that are used for differentiation of the function. In C++, this includes the function name, number of parameters, parameter type, and function-level qualifiers. It notably doesnotinclude the return type.Name manglingAs an aside\u2026When the compiler compiles a function, it performsname mangling, which means the compiled name of the function is altered (\u201cmangled\u201d) based on various criteria, such as the number and type of parameters, so that the linker has unique names to work with.For example, a function with prototypeint fcn()might compile to mangled name__fcn_v, whereasint fcn(int)might compile to mangled name__fcn_i. So while in the source code, the two overloaded functions share the namefcn(), in compiled code, the mangled names are unique (__fcn_vvs__fcn_i).There is no standardization on how names should be mangled, so different compilers will produce different mangled names.Next lesson11.3Function overload resolution and ambiguous matchesBack to table of contentsPrevious lesson11.1Introduction to function overloading"
        },
        {
          "code": "error C2556: 'double getRandomValue(void)': overloaded function differs only by return type from 'int getRandomValue(void)'\n"
        },
        {
          "text": "This makes sense. If you were the compiler, and you saw this statement:getRandomValue();Which of the two overloaded functions would you call? It\u2019s not clear.As an aside\u2026This was an intentional choice, as it ensures the behavior of a function call can be determined independently from the rest of the expression, making understanding complex expressions much simpler. Put another way, we can always determine which version of a function will be called based solely on the arguments in the function call. If return values were used for differentiation, then we wouldn\u2019t have an easy syntactic way to tell which overload of a function was being called -- we\u2019d also have to understand how the return value was being used, which requires a lot more analysis.The best way to address this is to give the functions different names:int getRandomInt();\ndouble getRandomDouble();Type signatureA function\u2019stype signature(generally called asignature) is defined as the parts of the function header that are used for differentiation of the function. In C++, this includes the function name, number of parameters, parameter type, and function-level qualifiers. It notably doesnotinclude the return type.Name manglingAs an aside\u2026When the compiler compiles a function, it performsname mangling, which means the compiled name of the function is altered (\u201cmangled\u201d) based on various criteria, such as the number and type of parameters, so that the linker has unique names to work with.For example, a function with prototypeint fcn()might compile to mangled name__fcn_v, whereasint fcn(int)might compile to mangled name__fcn_i. So while in the source code, the two overloaded functions share the namefcn(), in compiled code, the mangled names are unique (__fcn_vvs__fcn_i).There is no standardization on how names should be mangled, so different compilers will produce different mangled names.Next lesson11.3Function overload resolution and ambiguous matchesBack to table of contentsPrevious lesson11.1Introduction to function overloading"
        },
        {
          "code": "getRandomValue();"
        },
        {
          "text": "Which of the two overloaded functions would you call? It\u2019s not clear.As an aside\u2026This was an intentional choice, as it ensures the behavior of a function call can be determined independently from the rest of the expression, making understanding complex expressions much simpler. Put another way, we can always determine which version of a function will be called based solely on the arguments in the function call. If return values were used for differentiation, then we wouldn\u2019t have an easy syntactic way to tell which overload of a function was being called -- we\u2019d also have to understand how the return value was being used, which requires a lot more analysis.The best way to address this is to give the functions different names:int getRandomInt();\ndouble getRandomDouble();Type signatureA function\u2019stype signature(generally called asignature) is defined as the parts of the function header that are used for differentiation of the function. In C++, this includes the function name, number of parameters, parameter type, and function-level qualifiers. It notably doesnotinclude the return type.Name manglingAs an aside\u2026When the compiler compiles a function, it performsname mangling, which means the compiled name of the function is altered (\u201cmangled\u201d) based on various criteria, such as the number and type of parameters, so that the linker has unique names to work with.For example, a function with prototypeint fcn()might compile to mangled name__fcn_v, whereasint fcn(int)might compile to mangled name__fcn_i. So while in the source code, the two overloaded functions share the namefcn(), in compiled code, the mangled names are unique (__fcn_vvs__fcn_i).There is no standardization on how names should be mangled, so different compilers will produce different mangled names.Next lesson11.3Function overload resolution and ambiguous matchesBack to table of contentsPrevious lesson11.1Introduction to function overloading"
        },
        {
          "text": "As an aside\u2026This was an intentional choice, as it ensures the behavior of a function call can be determined independently from the rest of the expression, making understanding complex expressions much simpler. Put another way, we can always determine which version of a function will be called based solely on the arguments in the function call. If return values were used for differentiation, then we wouldn\u2019t have an easy syntactic way to tell which overload of a function was being called -- we\u2019d also have to understand how the return value was being used, which requires a lot more analysis."
        },
        {
          "text": "This was an intentional choice, as it ensures the behavior of a function call can be determined independently from the rest of the expression, making understanding complex expressions much simpler. Put another way, we can always determine which version of a function will be called based solely on the arguments in the function call. If return values were used for differentiation, then we wouldn\u2019t have an easy syntactic way to tell which overload of a function was being called -- we\u2019d also have to understand how the return value was being used, which requires a lot more analysis."
        },
        {
          "text": "The best way to address this is to give the functions different names:int getRandomInt();\ndouble getRandomDouble();Type signatureA function\u2019stype signature(generally called asignature) is defined as the parts of the function header that are used for differentiation of the function. In C++, this includes the function name, number of parameters, parameter type, and function-level qualifiers. It notably doesnotinclude the return type.Name manglingAs an aside\u2026When the compiler compiles a function, it performsname mangling, which means the compiled name of the function is altered (\u201cmangled\u201d) based on various criteria, such as the number and type of parameters, so that the linker has unique names to work with.For example, a function with prototypeint fcn()might compile to mangled name__fcn_v, whereasint fcn(int)might compile to mangled name__fcn_i. So while in the source code, the two overloaded functions share the namefcn(), in compiled code, the mangled names are unique (__fcn_vvs__fcn_i).There is no standardization on how names should be mangled, so different compilers will produce different mangled names.Next lesson11.3Function overload resolution and ambiguous matchesBack to table of contentsPrevious lesson11.1Introduction to function overloading"
        },
        {
          "code": "int getRandomInt();\ndouble getRandomDouble();"
        },
        {
          "text": "Type signatureA function\u2019stype signature(generally called asignature) is defined as the parts of the function header that are used for differentiation of the function. In C++, this includes the function name, number of parameters, parameter type, and function-level qualifiers. It notably doesnotinclude the return type.Name manglingAs an aside\u2026When the compiler compiles a function, it performsname mangling, which means the compiled name of the function is altered (\u201cmangled\u201d) based on various criteria, such as the number and type of parameters, so that the linker has unique names to work with.For example, a function with prototypeint fcn()might compile to mangled name__fcn_v, whereasint fcn(int)might compile to mangled name__fcn_i. So while in the source code, the two overloaded functions share the namefcn(), in compiled code, the mangled names are unique (__fcn_vvs__fcn_i).There is no standardization on how names should be mangled, so different compilers will produce different mangled names.Next lesson11.3Function overload resolution and ambiguous matchesBack to table of contentsPrevious lesson11.1Introduction to function overloading"
        },
        {
          "text": "A function\u2019stype signature(generally called asignature) is defined as the parts of the function header that are used for differentiation of the function. In C++, this includes the function name, number of parameters, parameter type, and function-level qualifiers. It notably doesnotinclude the return type.Name manglingAs an aside\u2026When the compiler compiles a function, it performsname mangling, which means the compiled name of the function is altered (\u201cmangled\u201d) based on various criteria, such as the number and type of parameters, so that the linker has unique names to work with.For example, a function with prototypeint fcn()might compile to mangled name__fcn_v, whereasint fcn(int)might compile to mangled name__fcn_i. So while in the source code, the two overloaded functions share the namefcn(), in compiled code, the mangled names are unique (__fcn_vvs__fcn_i).There is no standardization on how names should be mangled, so different compilers will produce different mangled names.Next lesson11.3Function overload resolution and ambiguous matchesBack to table of contentsPrevious lesson11.1Introduction to function overloading"
        },
        {
          "text": "Name manglingAs an aside\u2026When the compiler compiles a function, it performsname mangling, which means the compiled name of the function is altered (\u201cmangled\u201d) based on various criteria, such as the number and type of parameters, so that the linker has unique names to work with.For example, a function with prototypeint fcn()might compile to mangled name__fcn_v, whereasint fcn(int)might compile to mangled name__fcn_i. So while in the source code, the two overloaded functions share the namefcn(), in compiled code, the mangled names are unique (__fcn_vvs__fcn_i).There is no standardization on how names should be mangled, so different compilers will produce different mangled names.Next lesson11.3Function overload resolution and ambiguous matchesBack to table of contentsPrevious lesson11.1Introduction to function overloading"
        },
        {
          "text": "As an aside\u2026When the compiler compiles a function, it performsname mangling, which means the compiled name of the function is altered (\u201cmangled\u201d) based on various criteria, such as the number and type of parameters, so that the linker has unique names to work with.For example, a function with prototypeint fcn()might compile to mangled name__fcn_v, whereasint fcn(int)might compile to mangled name__fcn_i. So while in the source code, the two overloaded functions share the namefcn(), in compiled code, the mangled names are unique (__fcn_vvs__fcn_i).There is no standardization on how names should be mangled, so different compilers will produce different mangled names."
        },
        {
          "text": "When the compiler compiles a function, it performsname mangling, which means the compiled name of the function is altered (\u201cmangled\u201d) based on various criteria, such as the number and type of parameters, so that the linker has unique names to work with.For example, a function with prototypeint fcn()might compile to mangled name__fcn_v, whereasint fcn(int)might compile to mangled name__fcn_i. So while in the source code, the two overloaded functions share the namefcn(), in compiled code, the mangled names are unique (__fcn_vvs__fcn_i).There is no standardization on how names should be mangled, so different compilers will produce different mangled names."
        },
        {
          "text": "For example, a function with prototypeint fcn()might compile to mangled name__fcn_v, whereasint fcn(int)might compile to mangled name__fcn_i. So while in the source code, the two overloaded functions share the namefcn(), in compiled code, the mangled names are unique (__fcn_vvs__fcn_i).There is no standardization on how names should be mangled, so different compilers will produce different mangled names."
        },
        {
          "text": "There is no standardization on how names should be mangled, so different compilers will produce different mangled names."
        }
      ]
    }
  ],
  "quiz": []
}